todowrite_cli/__init__.py
todowrite_cli/__main__.py
todowrite_cli/main.py
todowrite_cli/version.py
todowrite_cli-0.4.1.dist-info/METADATA
todowrite_cli-0.4.1.dist-info/WHEEL
todowrite_cli-0.4.1.dist-info/entry_points.txt
todowrite_cli-0.4.1.dist-info/licenses/LICENSE
todowrite_cli-0.4.1.dist-info/RECORD
